AUTHORS
CHANGELOG.txt
DESCRIPTION
LICENSE
MANIFEST.in
README.rst
setup.py
django_linklist.egg-info/PKG-INFO
django_linklist.egg-info/SOURCES.txt
django_linklist.egg-info/dependency_links.txt
django_linklist.egg-info/top_level.txt
linklist/__init__.py
linklist/admin.py
linklist/models.py
linklist/migrations/0001_initial.py
linklist/migrations/0002_auto__chg_field_link_image__add_field_linkcategory_slug.py
linklist/migrations/__init__.py
linklist/templatetags/__init__.py
linklist/templatetags/linklist_tags.py
linklist/tests/__init__.py
linklist/tests/factories.py
linklist/tests/linklist_tags_tests.py
linklist/tests/models_tests.py
linklist/tests/runtests.py
linklist/tests/south_settings.py
linklist/tests/test_settings.py
linklist/tests/urls.py
linklist/tests/test_app/__init__.py
linklist/tests/test_app/models.py
linklist/tests/test_app/templates/404.html
linklist/tests/test_app/templates/base.html