Metadata-Version: 1.0
Name: django-linklist
Version: 0.3
Summary: Django app to render a list of links with some meta information and a screenshot.
